{
  "source": "contents-051",
  "problemCategory": "キャリア・職業選択",
  "problemDescription": "休日をしっかり取りたいが給料も下げたくない。お給料は上げたいけど休日は欲しい、できるなら稼ぎたい、仕事と休日のバランスが大事という働き方の悩み",
  "postType": "003",
  "postTypeReason": "9つの職業について年収・休日数・特徴を具体的に解説する情報提供型コンテンツ。「意外と知らない」というタイトルから特定の情報・知識の習得を目的としている",
  "solutionContent": {
    "概要": "休日が多くて稼げる9つの職業を年収・平均年間休日・特徴とともに紹介",
    "具体的手順": [
      "自己分析をして自分の強みや弱みを理解する",
      "紹介された職業の中から自分に適したものを検討する",
      "各職業の年収と休日数を比較検討する",
      "必要なスキルや専門知識を把握する"
    ],
    "提供情報": [
      "ITエンジニア（年収438万円、休日125日）",
      "銀行員（年収608万円、休日120日）",
      "MR（年収713万円、休日133日）",
      "コンサルタント（年収575万円、休日122日）",
      "企画職（年収529万円、休日127日）",
      "機電系エンジニア（年収444万円、休日130日）",
      "研究職（年収565万円、休日134日）",
      "大学職員（年収442万円、休日120日）",
      "営業職（年収435万円、休日124日）"
    ],
    "実用的なアドバイス": [
      "まずは自己分析をして自分の強みや弱みを理解する",
      "土日祝が休み、待遇が良い業界を選ぶ",
      "法人を相手にしている職業を検討する",
      "専門性が高い職業ほど年収も高めになる"
    ]
  },
  "effectiveExpressions": [
    "タイトルページ：ベージュ系背景に人物写真、大きな円形レイアウトで「9選」を強調",
    "問題提起ページ：白背景にチェックボックス付きリスト、イラスト付きで共感を誘う",
    "各職業紹介：統一されたPoint番号デザイン、職業アイコン、年収・休日数を赤字で強調",
    "まとめページ：特徴を箇条書きで整理、自己分析ツールの紹介",
    "CTA ページ：フォロー促進とストーリー限定情報の告知"
  ],
  "searchKeywords": [
    "休日多い仕事",
    "高収入",
    "ワークライフバランス",
    "年収",
    "転職",
    "職業選択",
    "ITエンジニア",
    "銀行員",
    "MR",
    "コンサルタント",
    "企画職",
    "研究職"
  ],
  "emotionalTriggers": [
    "仕事と休日のバランスに悩む人への具体的選択肢の提示",
    "年収と休日数の具体的数値による信頼性",
    "自己分析による適職発見への導き",
    "働き方の選択肢拡大による安心感の提供"
  ],
  "marketingStage": "転職検討中・キャリアチェンジを考えている社会人、新卒で職業選択に悩む学生",
  "knowledgeId": "K051",
  "pageStructurePattern": "typeID003-industry-ranking-list",
  "actualTitle": "意外と知らない 休日が多くて稼げる仕事 9選",
  "pageCount": 9,
  "hashTag": "#仕事 #退職 #転職について毎日発信",
  "detailedContent": {
    "page1": {
      "type": "title",
      "content": {
        "mainTitle": "意外と知らない",
        "subTitle": "休日が多くて稼げる仕事",
        "highlight": "9選",
        "background": "ベージュ系グラデーション背景",
        "personImage": "マスク着用女性のポーズ写真",
        "pageIndicator": "1/9"
      }
    },
    "page2": {
      "type": "problem-identification",
      "content": {
        "header": "できれば休日はしっかりとりたい",
        "question": "あなたはこんなことない？",
        "checklist": [
          "お給料は上げたいけど休日は欲しい",
          "できるなら稼ぎたい",
          "仕事と休日のバランスが大事"
        ],
        "illustration": "悩んでいる女性のイラスト",
        "ctaText": "そんな条件を叶えてくれるお仕事はコレ！",
        "pageIndicator": "2/9"
      }
    },
    "page3": {
      "type": "job-introduction",
      "content": {
        "pointNumber": "1",
        "jobTitle": "ITエンジニア",
        "icon": "女性とPC のイラスト",
        "averageIncome": "438万円",
        "averageHolidays": "125日",
        "description": "ただしプロジェクトの納期やトラブル対応などによって休日出勤が必要になることも。",
        "pageIndicator": "3/9"
      }
    },
    "page4": {
      "type": "job-introduction",
      "content": {
        "pointNumber": "2",
        "jobTitle": "銀行員",
        "icon": "銀行ビルのイラスト",
        "averageIncome": "608万円", 
        "averageHolidays": "120日",
        "description": "休みはほぼカレンダー通りで休日出勤はほぼなし。",
        "pageIndicator": "4/9"
      }
    },
    "page5": {
      "type": "job-introduction",
      "content": {
        "pointNumber": "3",
        "jobTitle": "MR",
        "icon": "薬のイラスト",
        "averageIncome": "713万円",
        "averageHolidays": "133日", 
        "description": "年収も高い分、高い専門知識は必要。",
        "pageIndicator": "5/9"
      }
    },
    "page6": {
      "type": "job-introduction", 
      "content": {
        "pointNumber": "4",
        "jobTitle": "コンサルタント",
        "icon": "会議のイラスト",
        "averageIncome": "575万円",
        "averageHolidays": "122日",
        "description": "激務のコンサルタントもあるので求人をしっかり見極めることは重要。",
        "pageIndicator": "6/9"
      }
    },
    "page7": {
      "type": "job-introduction",
      "content": {
        "pointNumber": "5",
        "jobTitle": "企画職",
        "icon": "企画会議のイラスト",
        "averageIncome": "529万円",
        "averageHolidays": "127日",
        "description": "企画職はどの企業も少数精鋭の組織体制を取っていることもあって、平均年収は高めに。",
        "pageIndicator": "7/9"
      }
    },
    "page8": {
      "type": "job-introduction",
      "content": {
        "pointNumber": "6", 
        "jobTitle": "機電系エンジニア",
        "icon": "機械・歯車のイラスト",
        "averageIncome": "444万円",
        "averageHolidays": "130日",
        "description": "電子部品や機械製品の開発や製造を行うお仕事。",
        "pageIndicator": "8/9"
      }
    },
    "page9": {
      "type": "job-introduction",
      "content": {
        "pointNumber": "7",
        "jobTitle": "研究職", 
        "icon": "研究者のイラスト",
        "averageIncome": "565万円",
        "averageHolidays": "134日",
        "description": "専門性が高く、平均年収もそれに応じて高めに。",
        "pageIndicator": "9/9"
      }
    },
    "page10": {
      "type": "job-introduction",
      "content": {
        "pointNumber": "8",
        "jobTitle": "大学職員",
        "icon": "女性とPCのイラスト", 
        "averageIncome": "442万円",
        "averageHolidays": "120日",
        "description": "国公立大学か私立大学かによって待遇や仕事内容が変わることが多い。",
        "pageIndicator": "10/9"
      }
    },
    "page11": {
      "type": "job-introduction",
      "content": {
        "pointNumber": "9", 
        "jobTitle": "営業職",
        "icon": "プレゼンテーションのイラスト",
        "averageIncome": "435万円",
        "averageHolidays": "124日",
        "description": "求人をしっかり見極めれば、休日がしっかりあって年収が高めのお仕事も○",
        "pageIndicator": "11/9"
      }
    },
    "page12": {
      "type": "summary",
      "content": {
        "pointNumber": "10",
        "title": "休みが多くて稼げる仕事の特徴",
        "features": [
          "土日祝が休み",
          "待遇が良い業界（メーカー/インフラ/金融など）",
          "主に法人を相手にしている"
        ],
        "advice": "まずは自己分析をして自分の強みや弱みを理解するところから始めてみて○",
        "highlight": "ハイライトに自己分析法もまとめてるよ",
        "toolIcons": ["3分自己分析", "事務転職", "未経験転職", "キャリア○", "仕事探し"],
        "pageIndicator": "12/9"
      }
    },
    "page13": {
      "type": "cta",
      "content": {
        "message": "仕事/退職/転職について毎日発信",
        "subMessage": "悩んでる方はフォローしてね",
        "profilePreview": "Instagramアカウントプレビュー表示",
        "highlight": "ハイライトでは悩みの解決策もまとめてるよ",
        "storyNote": "ストーリーではフォロワーさん限定情報も発信〜",
        "pageIndicator": "13/9"
      }
    }
  }
}