{
  "id": "FC002",
  "name": "年間休日130日以上企業TOP10",
  "target": "女性キャリア",
  "criteria": "holidays",
  "limit": 10,
  "filters": {
    "holidaysRange": [
      130,
      null
    ]
  },
  "generatedAt": "2025-08-29T02:03:31.012Z",
  "resultCount": 3,
  "ranking": [
    {
      "rank": 1,
      "id": "HR007",
      "name": "UTグループ株式会社",
      "industry": "製造業向け人材サービス",
      "value": 193,
      "formattedValue": "193日",
      "metrics": {
        "salary": 500,
        "initialSalary": 240,
        "initialSalaryGrad": null,
        "holidays": 193,
        "overtime": null,
        "employees": 32000,
        "operatingMarginRate": null,
        "roe": null,
        "vacationRate": null,
        "parentalLeaveReturn": null,
        "maleParentalLeaveRate": null,
        "femaleParentalLeaveRate": null,
        "turnoverRate3Years": null,
        "averageTenure": 3.9
      },
      "features": {
        "businessModel": "製造業特化型人材派遣・請負",
        "specialization": "自動車・半導体・電子部品製造",
        "workStyle": "現場作業・技能職中心",
        "growth": "ものづくり人材育成・海外展開"
      },
      "welfare": {
        "housingAllowance": null,
        "transportationAllowance": null,
        "familyAllowance": null,
        "cafeteria": null,
        "trainingSupport": "技能研修制度",
        "uniqueBenefits": null,
        "welfareGrade": "C",
        "clubActivities": null
      },
      "description": "製造業向け人材サービス。自動車・半導体・電子部品製造、現場作業・技能職中心。"
    },
    {
      "rank": 2,
      "id": "RETAIL001",
      "name": "株式会社ファーストリテイリング",
      "industry": "アパレル製造小売業",
      "value": 135,
      "formattedValue": "135日",
      "metrics": {
        "salary": 901,
        "initialSalary": null,
        "initialSalaryGrad": null,
        "holidays": 135,
        "overtime": 16.3,
        "employees": 58000,
        "operatingMarginRate": null,
        "roe": null,
        "vacationRate": 74.6,
        "parentalLeaveReturn": null,
        "maleParentalLeaveRate": null,
        "femaleParentalLeaveRate": null,
        "turnoverRate3Years": null,
        "averageTenure": null
      },
      "features": {
        "businessModel": "「ユニクロ」「ジーユー」等を展開するアパレル製造小売業",
        "specialization": "「LifeWear = 新しい産業」戦略・サステナブル素材転換",
        "workStyle": null,
        "growth": "販売員キャリアパス改革・多様なキャリアパス提供"
      },
      "welfare": {
        "housingAllowance": null,
        "transportationAllowance": null,
        "familyAllowance": null,
        "cafeteria": null,
        "trainingSupport": null,
        "uniqueBenefits": null,
        "welfareGrade": "A",
        "clubActivities": null
      },
      "description": "アパレル製造小売業。「LifeWear = 新しい産業」戦略・サステナブル素材転換。"
    },
    {
      "rank": 3,
      "id": "HR019",
      "name": "ビジョナル株式会社",
      "industry": "HR Tech・求人プラットフォーム",
      "value": 130,
      "formattedValue": "130日",
      "metrics": {
        "salary": 650,
        "initialSalary": 335,
        "initialSalaryGrad": 335,
        "holidays": 130,
        "overtime": 26,
        "employees": 1200,
        "operatingMarginRate": 18.5,
        "roe": 12.5,
        "vacationRate": 85,
        "parentalLeaveReturn": 95,
        "maleParentalLeaveRate": 35,
        "femaleParentalLeaveRate": 100,
        "turnoverRate3Years": 8.5,
        "averageTenure": 4.2
      },
      "features": {
        "businessModel": "HR Tech・転職プラットフォーム運営",
        "specialization": "ビズリーチ・HRMOS・キャリトレ",
        "workStyle": "リモート・フレックス・裁量労働",
        "growth": "AI・データ分析・海外展開"
      },
      "welfare": {
        "housingAllowance": "住宅補助・引越し支援",
        "transportationAllowance": "全額支給",
        "familyAllowance": "家族手当・育児支援充実",
        "cafeteria": "社員食堂・軽食・ドリンク無料",
        "trainingSupport": "研修・書籍・カンファレンス参加支援",
        "uniqueBenefits": "株式付与・副業可・MacBook支給",
        "welfareGrade": "A",
        "clubActivities": "多数の部活動・社内イベント"
      },
      "description": "HR Tech・求人プラットフォーム。ビズリーチ・HRMOS・キャリトレ、リモート・フレックス・裁量労働。"
    }
  ]
}